django_env_loader/__init__.py
django_env_loader/exceptions.py
django_env_loader/loader.py
django_env_loader/py.typed
django_env_loader-1.0.5.dist-info/licenses/LICENSE
django_env_loader-1.0.5.dist-info/METADATA
django_env_loader-1.0.5.dist-info/WHEEL
django_env_loader-1.0.5.dist-info/RECORD
