Metadata-Version: 2.4
Name: django-env-loader
Version: 1.0.5
Summary: Gerenciador robusto de variáveis de ambiente e secrets para Django
License-Expression: MIT
License-File: LICENSE
Keywords: django,env,environment,secrets,docker
Author: Felipe Abreu
Author-email: felipeabreu.rj@gmail.com
Requires-Python: >=3.10
Classifier: Development Status :: 4 - Beta
Classifier: Intended Audience :: Developers
Classifier: Programming Language :: Python :: 3
Classifier: Programming Language :: Python :: 3.10
Classifier: Programming Language :: Python :: 3.11
Classifier: Programming Language :: Python :: 3.12
Classifier: Programming Language :: Python :: 3.13
Classifier: Topic :: Software Development :: Libraries :: Python Modules
Classifier: Framework :: Django
Requires-Dist: python-dotenv (>=1.0.0,<2.0.0)
Project-URL: Bug Tracker, https://github.com/felipeabreu86/django-env-loader/issues
Project-URL: Homepage, https://github.com/felipeabreu86/django-env-loader
Project-URL: Repository, https://github.com/felipeabreu86/django-env-loader
